react_sms_sdk_python/__init__.py
react_sms_sdk_python/react_sms.py
reactsms_sdk_python-0.3.dist-info/METADATA
reactsms_sdk_python-0.3.dist-info/WHEEL
reactsms_sdk_python-0.3.dist-info/top_level.txt
reactsms_sdk_python-0.3.dist-info/RECORD
