Metadata-Version: 2.1
Name: reactsms_sdk_python
Version: 0.3
Summary: React SMS SDK for Python
Home-page: https://github.com/hub-coffee/react-sms-sdk-python.git
Author: Huberson Kouakou
Author-email: huberson.kouakou@yahoo.com
Classifier: Programming Language :: Python :: 3
Classifier: License :: OSI Approved :: MIT License
Classifier: Operating System :: OS Independent
Requires-Python: >=3.6
Requires-Dist: requests==2.32.3
